bric_solar_simulator/__init__.py
bric_solar_simulator/app/__init__.py
bric_solar_simulator/controller/__init__.py
bric_solar_simulator/controller/icon.ico
bric_solar_simulator/controller/solar_simulator_controller.py
bric_solar_simulator/interface/RGBUV_Controller.h
bric_solar_simulator/interface/__init__.py
bric_solar_simulator/interface/solar_simulator_controller.py
bric_solar_simulator/interface/solar_simulator_interface.py
bric_solar_simulator/interface/yellow-light.png
bric_solar_simulator-0.0.2.dist-info/LICENSE
bric_solar_simulator-0.0.2.dist-info/METADATA
bric_solar_simulator-0.0.2.dist-info/WHEEL
bric_solar_simulator-0.0.2.dist-info/solar_simulator_controller.py
bric_solar_simulator-0.0.2.dist-info/solar_simulator_interface.py
bric_solar_simulator-0.0.2.dist-info/top_level.txt
bric_solar_simulator-0.0.2.dist-info/RECORD
