Metadata-Version: 2.1
Name: bric-solar-simulator
Version: 0.0.2
Summary: Control and interface for Arduino driven, LED solar simulator.
Home-page: UNKNOWN
Author: Brian Carlsen
Author-email: carlsen.bri@gmail.com
License: UNKNOWN
Platform: UNKNOWN
Classifier: Programming Language :: Python :: 3
Classifier: License :: OSI Approved :: MIT License
Classifier: Operating System :: OS Independent
Classifier: Development Status :: 3 - Alpha
Requires-Dist: bric-arduino-controllers
